example_pkg/__init__.py
six_pack_trade_algo/Bb.py
six_pack_trade_algo/GME.py
six_pack_trade_algo/__init__.py
six_pack_trade_algo/algos.py
six_pack_trade_algo/creds.py
six_pack_trade_algo/main.py
six_pack_trade_algo/order.py
six_pack_trade_algo/rebalancer.py
six_pack_trade_algo/rsi.py
six_pack_trade_algo/rsi_bb.py
six_pack_trade_algo/runner.py
six_pack_trade_algo/test.py
six_pack_trade_algo/util.py
source/__init__.py
six_pack_trade_algo-0.0.493.dist-info/LICENSE
six_pack_trade_algo-0.0.493.dist-info/METADATA
six_pack_trade_algo-0.0.493.dist-info/WHEEL
six_pack_trade_algo-0.0.493.dist-info/top_level.txt
six_pack_trade_algo-0.0.493.dist-info/RECORD
